{ "portland": [{
    "image": " Piper At The Gates of Dawn",
    "title": "Best Restaurant in portland",
    "id": "1"
    }, {
    "image": " Piper At The Gates of Dawn",
    "title": "New Restaurant and Bars in portland",
    "id": "2"
      }, {
    "image": " Piper At The Gates of Dawn",
    "title": "Hottest Restaurants and Bars in Portland, OR",
    "id": "3"
    }, {
    "image": " Piper At The Gates of Dawn",
    "title": "Restaurants & Bars Near the Portland Museum of Art",
    "id": "4"
  }]
}
